omamer/__init__.py
omamer/_clock.py
omamer/_runners.py
omamer/_utils.py
omamer/alphabets.py
omamer/database.py
omamer/hierarchy.py
omamer/index.py
omamer/main.py
omamer/merge_search.py
omamer/orthoxml_parser.py
omamer/results_reader.py
omamer/sequence_buffer.py
omamer/sequence_reader.py
omamer-2.1.2.dist-info/licenses/COPYING
omamer-2.1.2.dist-info/licenses/COPYING.LESSER
omamer-2.1.2.dist-info/licenses/LICENSE
omamer-2.1.2.dist-info/METADATA
omamer-2.1.2.dist-info/WHEEL
omamer-2.1.2.dist-info/entry_points.txt
omamer-2.1.2.dist-info/top_level.txt
omamer-2.1.2.dist-info/RECORD
