Metadata-Version: 2.4
Name: omamer
Version: 2.1.2
Summary: OMAmer - tree-driven and alignment-free protein assignment to sub-families
Home-page: https://github.com/DessimozLab/omamer
Author: Victor Rossier and Alex Warwick Vesztrocy
License: LGPLv3
Requires-Python: >=3.8
License-File: LICENSE
License-File: COPYING
License-File: COPYING.LESSER
Requires-Dist: alive_progress
Requires-Dist: biopython
Requires-Dist: ete3
Requires-Dist: lxml
Requires-Dist: numba
Requires-Dist: numpy<2
Requires-Dist: pandas>2.0.0
Requires-Dist: property_manager
Requires-Dist: Rmath4
Requires-Dist: scipy
Requires-Dist: tables
Requires-Dist: tqdm
Provides-Extra: build
Requires-Dist: pysais; extra == "build"
Dynamic: author
Dynamic: home-page
Dynamic: license
Dynamic: license-file
Dynamic: provides-extra
Dynamic: requires-dist
Dynamic: requires-python
Dynamic: summary
